beproud.utils-0.34-py2.7-nspkg.pth
beproud/utils/__init__.py
beproud/utils/datastructures.py
beproud/utils/decimalutils.py
beproud/utils/html.py
beproud/utils/javascript.py
beproud/utils/strutils.py
beproud/utils/word.py
beproud/utils/dbutils/__init__.py
beproud/utils/dbutils/mysql.py
beproud/utils/tests/__init__.py
beproud/utils/tests/datastructures_tests.py
beproud/utils/tests/decimalutils_tests.py
beproud/utils/tests/html_tests.py
beproud/utils/tests/javascript_tests.py
beproud/utils/tests/mysql_tests.py
beproud/utils/tests/strutils_tests.py
beproud/utils/tests/word_tests.py
beproud.utils-0.34.dist-info/DESCRIPTION.rst
beproud.utils-0.34.dist-info/METADATA
beproud.utils-0.34.dist-info/metadata.json
beproud.utils-0.34.dist-info/namespace_packages.txt
beproud.utils-0.34.dist-info/RECORD
beproud.utils-0.34.dist-info/top_level.txt
beproud.utils-0.34.dist-info/WHEEL
beproud.utils-0.34.dist-info/zip-safe
