Metadata-Version: 2.0
Name: beproud.utils
Version: 0.34
Summary: Dependency free utilities
Home-page: UNKNOWN
Author: Ian Lewis
Author-email: ianmlewis@beproud.jp
License: UNKNOWN
Platform: UNKNOWN
Classifier: Development Status :: 3 - Alpha
Classifier: Programming Language :: Python
Classifier: Topic :: Software Development :: Libraries :: Python Modules
